djangofusion_dot/__init__.py
djangofusion_dot-0.1.0.dist-info/LICENSE
djangofusion_dot-0.1.0.dist-info/METADATA
djangofusion_dot-0.1.0.dist-info/WHEEL
djangofusion_dot-0.1.0.dist-info/top_level.txt
djangofusion_dot-0.1.0.dist-info/RECORD
