Metadata-Version: 2.1
Name: djangofusion-dot
Version: 0.1.0
Summary: A collection of common helpers for Django projects.
Home-page: https://github.com/username/djangofusion-dot
Author: Alex Sirait
Author-email: alex.sirait@satnusa.com
License: MIT
Classifier: Programming Language :: Python :: 3
Classifier: Framework :: Django
Classifier: License :: OSI Approved :: MIT License
Classifier: Operating System :: OS Independent
Requires-Python: >=3.6
License-File: LICENSE
Requires-Dist: Django>=3.0
